{
  "config": {
    "data": {
      "data_root": "D:\\PythonProject\\Quant\\data_baostock\\stock_hist\\hs300",
      "hs300_list_path": "D:\\PythonProject\\Quant\\data_baostock\\metadata\\stock_list_hs300.csv",
      "index_root": "D:\\PythonProject\\Quant\\data_baostock\\ak_index",
      "file_format": "auto",
      "max_files": 5,
      "main_board_only": false,
      "extra_factor_paths": [],
      "extra_source_module": null,
      "factor_catalog_path": "D:\\PythonProject\\Quant\\data_baostock\\factor_mining\\factor_catalog.json",
      "auto_load_catalog_factors": true
    },
    "factors": {
      "factor_freq": "W",
      "factor_list": "",
      "custom_factor_py": null,
      "list_factors": false,
      "lookback_days": 160,
      "min_ic_cross_section": 30,
      "label_task": "direction"
    },
    "stock_model": {
      "model_type": "decision_tree",
      "max_depth": 6,
      "min_samples_leaf": 200,
      "random_state": 42,
      "custom_model_py": null,
      "fgcl_seq_len": 30,
      "fgcl_future_look": 20,
      "fgcl_hidden_size": 128,
      "fgcl_num_layers": 2,
      "fgcl_num_factor": 48,
      "fgcl_gamma": 1.0,
      "fgcl_tau": 0.25,
      "fgcl_epochs": 200,
      "fgcl_lr": 9e-05,
      "fgcl_early_stop": 20,
      "fgcl_smooth_steps": 5,
      "fgcl_per_epoch_batch": 100,
      "fgcl_batch_size": -1,
      "fgcl_label_transform": "csranknorm",
      "fgcl_weight_decay": 0.0001,
      "fgcl_dropout": 0.0,
      "fgcl_device": "auto",
      "dafat_seq_len": 40,
      "dafat_hidden_size": 128,
      "dafat_num_layers": 2,
      "dafat_num_heads": 4,
      "dafat_ffn_mult": 4,
      "dafat_dropout": 0.1,
      "dafat_local_window": 20,
      "dafat_topk_ratio": 0.3,
      "dafat_vol_quantile": 0.4,
      "dafat_meso_scale": 5,
      "dafat_macro_scale": 20,
      "dafat_epochs": 200,
      "dafat_lr": 0.0001,
      "dafat_weight_decay": 0.0001,
      "dafat_early_stop": 20,
      "dafat_per_epoch_batch": 120,
      "dafat_batch_size": -1,
      "dafat_label_transform": "csranknorm",
      "dafat_mse_weight": 0.05,
      "dafat_use_dpe": true,
      "dafat_use_sparse_attn": true,
      "dafat_use_multiscale": true,
      "dafat_device": "auto"
    },
    "timing_model": {
      "model_type": "none",
      "vol_threshold": 0.0,
      "momentum_threshold": 0.0,
      "custom_model_py": null
    },
    "portfolio_opt": {
      "mode": "equal_weight",
      "max_weight": 0.25,
      "max_turnover": 1.2,
      "liquidity_scale": 3.0,
      "expected_return_weight": 1.0,
      "risk_aversion": 1.2,
      "style_penalty": 0.8,
      "industry_penalty": 0.7,
      "crowding_penalty": 0.5,
      "transaction_cost_penalty": 0.6,
      "max_iter": 220,
      "step_size": 0.08,
      "tolerance": 1e-06,
      "custom_model_py": null
    },
    "execution_model": {
      "model_type": "ideal_fill",
      "max_participation_rate": 0.15,
      "base_fill_rate": 0.95,
      "latency_bars": 0,
      "custom_model_py": null
    },
    "backtest": {
      "horizon": 3,
      "top_k": 3,
      "long_threshold": 0.5,
      "execution_scheme": "vwap30_vwap30",
      "fee_bps": 1.5,
      "slippage_bps": 1.5,
      "portfolio_mode": "equal_weight",
      "rebalance_stride": 3
    },
    "dates": {
      "train_start": "2023-01-01",
      "train_end": "2024-06-30",
      "test_start": "2024-07-01",
      "test_end": "2024-12-31"
    },
    "output_dir": "d:\\PythonProject\\Quant\\TradeSystem\\Strategy7\\outputs\\_tmp_freq_guard\\pipeline_W",
    "save_models": true
  },
  "sample_count": {
    "daily_rows": 3055,
    "minute_rows": 146640,
    "base_rows": 640,
    "train_rows": 355,
    "test_rows": 110,
    "trade_points": 8,
    "position_count": 24,
    "external_rows": {},
    "catalog_rows": {}
  },
  "selected_factors": [
    "ret_1",
    "ret_3",
    "ma_gap_6",
    "rv_12",
    "range_norm",
    "amount_ratio_12"
  ],
  "model_metrics": {
    "accuracy": 0.45454545454545453,
    "precision": 0.45454545454545453,
    "recall": 1.0,
    "auc": 0.5,
    "rank_corr": NaN,
    "target_mode": "binary",
    "direction_labeling": "native_binary",
    "reg_mae": 0.5000000000000002,
    "reg_rmse": 0.5000000000000001,
    "reg_r2": -0.00833333333333397,
    "reg_pearson_corr": NaN,
    "reg_target_std": 0.5002084636321551,
    "reg_pred_std": 0.0
  },
  "backtest_metrics": {
    "strategy": {
      "periods": 8.0,
      "periods_per_year": 17.333333333333332,
      "win_rate": 0.5,
      "avg_return": 0.02503085435325918,
      "cum_return": 0.18921724263922668,
      "annualized_return": 0.4556800426425469,
      "annualized_vol": 0.372705763639828,
      "sharpe": 1.164103656154984,
      "sortino": 3.9369933982804453,
      "max_drawdown": -0.054750750324503716,
      "calmar": 8.322809092875703,
      "profit_factor": 3.102177418781768,
      "avg_win": 0.073875925460654,
      "avg_loss": -0.023814216754135628
    },
    "benchmark": {
      "periods": 8.0,
      "periods_per_year": 17.333333333333332,
      "win_rate": 0.375,
      "avg_return": 0.01547735897874097,
      "cum_return": 0.10298773518750859,
      "annualized_return": 0.23662061023832903,
      "annualized_vol": 0.3717558750295668,
      "sharpe": 0.7216408409869519,
      "sortino": 2.6988618078855096,
      "max_drawdown": -0.06765145952069374,
      "calmar": 3.497642355608747,
      "profit_factor": 1.83941340610511,
      "avg_win": 0.09044176608582004,
      "avg_loss": -0.029501285285506475
    },
    "excess": {
      "periods": 8.0,
      "periods_per_year": 17.333333333333332,
      "win_rate": 0.875,
      "avg_return": 0.00955349537451821,
      "cum_return": 0.07835465117129403,
      "annualized_return": 0.17756123687557146,
      "annualized_vol": 0.05648339225338788,
      "sharpe": 2.9317275967087473,
      "sortino": NaN,
      "max_drawdown": -0.010115387055427472,
      "calmar": 17.55357811842701,
      "profit_factor": 8.555614291795324,
      "avg_win": 0.012363335721523159,
      "avg_loss": -0.010115387054516423
    },
    "benchmark_pool": {
      "periods": 8.0,
      "periods_per_year": 17.333333333333332,
      "win_rate": 0.375,
      "avg_return": 0.01547735897874097,
      "cum_return": 0.10298773518750859,
      "annualized_return": 0.23662061023832903,
      "annualized_vol": 0.3717558750295668,
      "sharpe": 0.7216408409869519,
      "sortino": 2.6988618078855096,
      "max_drawdown": -0.06765145952069374,
      "calmar": 3.497642355608747,
      "profit_factor": 1.83941340610511,
      "avg_win": 0.09044176608582004,
      "avg_loss": -0.029501285285506475
    },
    "benchmark_hs300": {
      "periods": 8.0,
      "periods_per_year": 17.333333333333332,
      "win_rate": 0.0,
      "avg_return": 0.0,
      "cum_return": 0.0,
      "annualized_return": 0.0,
      "annualized_vol": 0.0,
      "sharpe": NaN,
      "sortino": NaN,
      "max_drawdown": -1.000088900582341e-12,
      "calmar": 0.0,
      "profit_factor": NaN,
      "avg_win": NaN,
      "avg_loss": NaN
    },
    "benchmark_zz500": {
      "periods": 8.0,
      "periods_per_year": 17.333333333333332,
      "win_rate": 0.0,
      "avg_return": 0.0,
      "cum_return": 0.0,
      "annualized_return": 0.0,
      "annualized_vol": 0.0,
      "sharpe": NaN,
      "sortino": NaN,
      "max_drawdown": -1.000088900582341e-12,
      "calmar": 0.0,
      "profit_factor": NaN,
      "avg_win": NaN,
      "avg_loss": NaN
    },
    "benchmark_zz1000": {
      "periods": 8.0,
      "periods_per_year": 17.333333333333332,
      "win_rate": 0.0,
      "avg_return": 0.0,
      "cum_return": 0.0,
      "annualized_return": 0.0,
      "annualized_vol": 0.0,
      "sharpe": NaN,
      "sortino": NaN,
      "max_drawdown": -1.000088900582341e-12,
      "calmar": 0.0,
      "profit_factor": NaN,
      "avg_win": NaN,
      "avg_loss": NaN
    },
    "excess_vs_pool": {
      "periods": 8.0,
      "periods_per_year": 17.333333333333332,
      "win_rate": 0.875,
      "avg_return": 0.00955349537451821,
      "cum_return": 0.07835465117129403,
      "annualized_return": 0.17756123687557146,
      "annualized_vol": 0.05648339225338788,
      "sharpe": 2.9317275967087473,
      "sortino": NaN,
      "max_drawdown": -0.010115387055427472,
      "calmar": 17.55357811842701,
      "profit_factor": 8.555614291795324,
      "avg_win": 0.012363335721523159,
      "avg_loss": -0.010115387054516423
    },
    "excess_vs_hs300": {
      "periods": 8.0,
      "periods_per_year": 17.333333333333332,
      "win_rate": 0.5,
      "avg_return": 0.02503085435325918,
      "cum_return": 0.18921724263922668,
      "annualized_return": 0.4556800426425469,
      "annualized_vol": 0.372705763639828,
      "sharpe": 1.164103656154984,
      "sortino": 3.9369933982804453,
      "max_drawdown": -0.054750750324503716,
      "calmar": 8.322809092875703,
      "profit_factor": 3.102177418781768,
      "avg_win": 0.073875925460654,
      "avg_loss": -0.023814216754135628
    },
    "excess_vs_zz500": {
      "periods": 8.0,
      "periods_per_year": 17.333333333333332,
      "win_rate": 0.5,
      "avg_return": 0.02503085435325918,
      "cum_return": 0.18921724263922668,
      "annualized_return": 0.4556800426425469,
      "annualized_vol": 0.372705763639828,
      "sharpe": 1.164103656154984,
      "sortino": 3.9369933982804453,
      "max_drawdown": -0.054750750324503716,
      "calmar": 8.322809092875703,
      "profit_factor": 3.102177418781768,
      "avg_win": 0.073875925460654,
      "avg_loss": -0.023814216754135628
    },
    "excess_vs_zz1000": {
      "periods": 8.0,
      "periods_per_year": 17.333333333333332,
      "win_rate": 0.5,
      "avg_return": 0.02503085435325918,
      "cum_return": 0.18921724263922668,
      "annualized_return": 0.4556800426425469,
      "annualized_vol": 0.372705763639828,
      "sharpe": 1.164103656154984,
      "sortino": 3.9369933982804453,
      "max_drawdown": -0.054750750324503716,
      "calmar": 8.322809092875703,
      "profit_factor": 3.102177418781768,
      "avg_win": 0.073875925460654,
      "avg_loss": -0.023814216754135628
    },
    "annualization_periods_per_year": 17.333333333333332,
    "rebalance_overlap_possible": 0.0,
    "active_trade_ratio": 1.0,
    "portfolio_weighting_mode": "equal_weight",
    "portfolio_avg_turnover": 0.12499999999987499,
    "portfolio_avg_concentration": 0.33333333333266657,
    "portfolio_avg_entropy": 1.0986122886650111,
    "timing_avg_exposure": 1.0,
    "execution_avg_fill": 1.0
  },
  "model_ic_summary": {
    "obs": 0.0,
    "ic_mean": NaN,
    "ic_std": NaN,
    "ic_ir": NaN,
    "ic_positive_ratio": NaN,
    "ic_tstat": NaN,
    "rank_ic_mean": NaN,
    "rank_ic_std": NaN,
    "rank_ic_ir": NaN,
    "rank_ic_positive_ratio": NaN,
    "rank_ic_tstat": NaN
  },
  "model_score_spread": {
    "obs": 0.0,
    "spread_mean": NaN,
    "spread_std": NaN,
    "spread_ir": NaN
  },
  "factor_ic_top10": [
    {
      "obs": 0.0,
      "ic_mean": NaN,
      "ic_std": NaN,
      "ic_ir": NaN,
      "ic_positive_ratio": NaN,
      "ic_tstat": NaN,
      "rank_ic_mean": NaN,
      "rank_ic_std": NaN,
      "rank_ic_ir": NaN,
      "rank_ic_positive_ratio": NaN,
      "rank_ic_tstat": NaN,
      "factor": "ret_1"
    },
    {
      "obs": 0.0,
      "ic_mean": NaN,
      "ic_std": NaN,
      "ic_ir": NaN,
      "ic_positive_ratio": NaN,
      "ic_tstat": NaN,
      "rank_ic_mean": NaN,
      "rank_ic_std": NaN,
      "rank_ic_ir": NaN,
      "rank_ic_positive_ratio": NaN,
      "rank_ic_tstat": NaN,
      "factor": "ret_3"
    },
    {
      "obs": 0.0,
      "ic_mean": NaN,
      "ic_std": NaN,
      "ic_ir": NaN,
      "ic_positive_ratio": NaN,
      "ic_tstat": NaN,
      "rank_ic_mean": NaN,
      "rank_ic_std": NaN,
      "rank_ic_ir": NaN,
      "rank_ic_positive_ratio": NaN,
      "rank_ic_tstat": NaN,
      "factor": "ma_gap_6"
    },
    {
      "obs": 0.0,
      "ic_mean": NaN,
      "ic_std": NaN,
      "ic_ir": NaN,
      "ic_positive_ratio": NaN,
      "ic_tstat": NaN,
      "rank_ic_mean": NaN,
      "rank_ic_std": NaN,
      "rank_ic_ir": NaN,
      "rank_ic_positive_ratio": NaN,
      "rank_ic_tstat": NaN,
      "factor": "rv_12"
    },
    {
      "obs": 0.0,
      "ic_mean": NaN,
      "ic_std": NaN,
      "ic_ir": NaN,
      "ic_positive_ratio": NaN,
      "ic_tstat": NaN,
      "rank_ic_mean": NaN,
      "rank_ic_std": NaN,
      "rank_ic_ir": NaN,
      "rank_ic_positive_ratio": NaN,
      "rank_ic_tstat": NaN,
      "factor": "range_norm"
    },
    {
      "obs": 0.0,
      "ic_mean": NaN,
      "ic_std": NaN,
      "ic_ir": NaN,
      "ic_positive_ratio": NaN,
      "ic_tstat": NaN,
      "rank_ic_mean": NaN,
      "rank_ic_std": NaN,
      "rank_ic_ir": NaN,
      "rank_ic_positive_ratio": NaN,
      "rank_ic_tstat": NaN,
      "factor": "amount_ratio_12"
    }
  ],
  "outputs": {
    "predictions_csv": "d:\\PythonProject\\Quant\\TradeSystem\\Strategy7\\outputs\\_tmp_freq_guard\\pipeline_W\\predictions_W_h3_allboards_equal_weight_edb61102ec.csv",
    "trades_csv": "d:\\PythonProject\\Quant\\TradeSystem\\Strategy7\\outputs\\_tmp_freq_guard\\pipeline_W\\trades_W_h3_allboards_equal_weight_edb61102ec.csv",
    "positions_csv": "d:\\PythonProject\\Quant\\TradeSystem\\Strategy7\\outputs\\_tmp_freq_guard\\pipeline_W\\positions_W_h3_allboards_equal_weight_edb61102ec.csv",
    "curve_csv": "d:\\PythonProject\\Quant\\TradeSystem\\Strategy7\\outputs\\_tmp_freq_guard\\pipeline_W\\curve_W_h3_allboards_equal_weight_edb61102ec.csv",
    "factor_ic_summary_csv": "d:\\PythonProject\\Quant\\TradeSystem\\Strategy7\\outputs\\_tmp_freq_guard\\pipeline_W\\factor_ic_summary_W_h3_allboards_equal_weight_edb61102ec.csv",
    "factor_ic_series_csv": "d:\\PythonProject\\Quant\\TradeSystem\\Strategy7\\outputs\\_tmp_freq_guard\\pipeline_W\\factor_ic_series_W_h3_allboards_equal_weight_edb61102ec.csv",
    "model_ic_series_csv": "d:\\PythonProject\\Quant\\TradeSystem\\Strategy7\\outputs\\_tmp_freq_guard\\pipeline_W\\model_ic_series_W_h3_allboards_equal_weight_edb61102ec.csv",
    "factor_library_csv": "d:\\PythonProject\\Quant\\TradeSystem\\Strategy7\\outputs\\_tmp_freq_guard\\pipeline_W\\factor_library_W_h3_allboards_equal_weight_edb61102ec.csv",
    "backtest_main_plot_png": "d:\\PythonProject\\Quant\\TradeSystem\\Strategy7\\outputs\\_tmp_freq_guard\\pipeline_W\\backtest_curve_main_W_h3_allboards_equal_weight_edb61102ec.png",
    "backtest_excess_plot_png": "d:\\PythonProject\\Quant\\TradeSystem\\Strategy7\\outputs\\_tmp_freq_guard\\pipeline_W\\backtest_curve_excess_W_h3_allboards_equal_weight_edb61102ec.png",
    "plot_main_generated": true,
    "plot_excess_generated": true,
    "save_models_enabled": true,
    "model_files": {
      "stock_model": {
        "model_pkl": "d:\\PythonProject\\Quant\\TradeSystem\\Strategy7\\outputs\\_tmp_freq_guard\\pipeline_W\\models\\stock_model_tree_W_h3_allboards_equal_weight_edb61102ec.pkl",
        "meta_json": "d:\\PythonProject\\Quant\\TradeSystem\\Strategy7\\outputs\\_tmp_freq_guard\\pipeline_W\\models\\stock_model_tree_W_h3_allboards_equal_weight_edb61102ec.json"
      },
      "timing_model": {
        "meta_json": "d:\\PythonProject\\Quant\\TradeSystem\\Strategy7\\outputs\\_tmp_freq_guard\\pipeline_W\\models\\timing_none_W_h3_allboards_equal_weight_edb61102ec.json"
      },
      "portfolio_model": {
        "meta_json": "d:\\PythonProject\\Quant\\TradeSystem\\Strategy7\\outputs\\_tmp_freq_guard\\pipeline_W\\models\\portfolio_equal_W_h3_allboards_equal_weight_edb61102ec.json"
      },
      "execution_model": {
        "meta_json": "d:\\PythonProject\\Quant\\TradeSystem\\Strategy7\\outputs\\_tmp_freq_guard\\pipeline_W\\models\\execution_ideal_W_h3_allboards_equal_weight_edb61102ec.json"
      }
    }
  },
  "notes": {
    "no_future_leakage": "factor features only use current/past information; labels use shifted future window;train/test split constrained by signal timestamps and target end timestamps.",
    "feature_fill_method": "median",
    "feature_fill_fit_scope": "train_only",
    "timing_model_enabled": false,
    "portfolio_dynamic_enabled": false,
    "realistic_execution_enabled": false,
    "model_persistence": "model files are saved only when --save-models is set; otherwise no models directory/files are created.",
    "catalog_factors_enabled": true,
    "catalog_factor_count": 0,
    "factor_catalog_path": "D:\\PythonProject\\Quant\\data_baostock\\factor_mining\\factor_catalog.json"
  }
}